tellibot/__init__.py
tellibot/argparse.py
tellibot/model.py
tellibot/tellibot.py
tellibot/interpreter/__init__.py
tellibot/interpreter/interpreter.py
tellibot/interpreter/tellibot.py
tellibot/interpreter/statements/__init__.py
tellibot/interpreter/statements/bot_admin_word.py
tellibot/interpreter/statements/bot_def_command.py
tellibot/interpreter/statements/bot_handle_admin_message.py
tellibot/interpreter/statements/bot_handle_message.py
tellibot/interpreter/statements/bot_send_response.py
tellibot/interpreter/statements/bot_set_admin_username.py
tellibot/interpreter/statements/bot_set_buttons.py
tellibot/interpreter/statements/bot_set_token.py
tellibot/interpreter/statements/bot_set_username.py
tellibot/interpreter/statements/bot_wait_for.py
tellibot/interpreter/statements/controls_flow_statements.py
tellibot/interpreter/statements/controls_for.py
tellibot/interpreter/statements/controls_forEach.py
tellibot/interpreter/statements/controls_repeat_ext.py
tellibot/interpreter/statements/controls_whileUntil.py
tellibot/interpreter/statements/db_connect.py
tellibot/interpreter/statements/db_create_table.py
tellibot/interpreter/statements/db_delete_data.py
tellibot/interpreter/statements/db_delete_table.py
tellibot/interpreter/statements/db_insert.py
tellibot/interpreter/statements/db_read.py
tellibot/interpreter/statements/db_update.py
tellibot/interpreter/statements/dict_create_with.py
tellibot/interpreter/statements/dict_get_all_keys.py
tellibot/interpreter/statements/dict_get_value.py
tellibot/interpreter/statements/dict_key_exist.py
tellibot/interpreter/statements/dict_pair.py
tellibot/interpreter/statements/dict_parse.py
tellibot/interpreter/statements/dict_set_value.py
tellibot/interpreter/statements/function_procedures_callnoreturn.py
tellibot/interpreter/statements/function_procedures_callreturn.py
tellibot/interpreter/statements/function_procedures_defnoreturn.py
tellibot/interpreter/statements/function_procedures_defreturn.py
tellibot-1.0.9.dist-info/LICENSE.txt
tellibot-1.0.9.dist-info/METADATA
tellibot-1.0.9.dist-info/WHEEL
tellibot-1.0.9.dist-info/entry_points.txt
tellibot-1.0.9.dist-info/top_level.txt
tellibot-1.0.9.dist-info/RECORD
