Metadata-Version: 2.1
Name: tellibot
Version: 1.0.9
Summary: A drag and drop programming to create telegram bot
Home-page: https://github.com/whoisjeeva/tellibot
Author: Jeeva
Author-email: support@gumify.me
License: MIT
Classifier: Programming Language :: Python :: 3
Classifier: License :: OSI Approved :: MIT License
Classifier: Operating System :: OS Independent
Requires-Python: >=3.10
License-File: LICENSE.txt
Requires-Dist: anyio ==4.3.0
Requires-Dist: bidict ==0.23.1
Requires-Dist: blinker ==1.8.0
Requires-Dist: certifi ==2024.2.2
Requires-Dist: charset-normalizer ==3.3.2
Requires-Dist: click ==8.1.7
Requires-Dist: colorama ==0.4.6
Requires-Dist: docutils ==0.21.2
Requires-Dist: Flask ==3.0.3
Requires-Dist: Flask-SocketIO ==5.3.6
Requires-Dist: h11 ==0.14.0
Requires-Dist: httpcore ==1.0.5
Requires-Dist: httpx ==0.27.0
Requires-Dist: idna ==3.7
Requires-Dist: importlib-metadata ==7.1.0
Requires-Dist: itsdangerous ==2.2.0
Requires-Dist: jaraco.classes ==3.4.0
Requires-Dist: jaraco.context ==5.3.0
Requires-Dist: jaraco.functools ==4.0.1
Requires-Dist: Jinja2 ==3.1.3
Requires-Dist: keyring ==25.2.0
Requires-Dist: markdown-it-py ==3.0.0
Requires-Dist: MarkupSafe ==2.1.5
Requires-Dist: mdurl ==0.1.2
Requires-Dist: more-itertools ==10.2.0
Requires-Dist: nh3 ==0.2.17
Requires-Dist: peewee ==3.17.3
Requires-Dist: pkginfo ==1.10.0
Requires-Dist: Pygments ==2.17.2
Requires-Dist: PyMySQL ==1.1.0
Requires-Dist: python-engineio ==4.9.0
Requires-Dist: python-socketio ==5.11.2
Requires-Dist: python-telegram-bot ==21.1.1
Requires-Dist: pywin32-ctypes ==0.2.2
Requires-Dist: readme-renderer ==43.0
Requires-Dist: requests ==2.31.0
Requires-Dist: requests-toolbelt ==1.0.0
Requires-Dist: rfc3986 ==2.0.0
Requires-Dist: rich ==13.7.1
Requires-Dist: simple-websocket ==1.0.0
Requires-Dist: sniffio ==1.3.1
